nams/arguments.py
nams/core.py
nams/interface.py
nams/setup_logger.py
network_automation_simplified-0.7.1.dist-info/METADATA
network_automation_simplified-0.7.1.dist-info/WHEEL
network_automation_simplified-0.7.1.dist-info/top_level.txt
network_automation_simplified-0.7.1.dist-info/RECORD
