Metadata-Version: 2.1
Name: network-automation-simplified
Version: 0.7.1
Summary: Network Automation Simplified
Home-page: https://pypi.org/project/network-automation-simplified/
Author: Cox Communications Inc.
Author-email: jason.cole@cox.com
License: UNKNOWN
Keywords: ncclient,nornir,jsnapy
Platform: UNKNOWN
Classifier: Development Status :: 3 - Alpha
Classifier: Topic :: System :: Networking
Classifier: License :: OSI Approved :: MIT License
Classifier: Programming Language :: Python :: 3.7
Requires-Python: >=3.7
Requires-Dist: jsnapy
Requires-Dist: xmltodict
Requires-Dist: nornir
Requires-Dist: recordclass
